lementpro/__init__.py
lementpro/builders.py
lementpro/logger.py
lementpro/sender.py
lementpro/data/__init__.py
lementpro/data/accesstokenmodel.py
lementpro/data/actionlogentryinfomodel.py
lementpro/data/attributeaddmodel.py
lementpro/data/attributeaddrelationmodel.py
lementpro/data/attributeaddresultmodel.py
lementpro/data/attributeextendedmodel.py
lementpro/data/attributeinfomodel.py
lementpro/data/attributepagingmodel.py
lementpro/data/attributepatchmodel.py
lementpro/data/attributepatchrelationmodel.py
lementpro/data/attributerelationinfomodel.py
lementpro/data/changepasswordmodel.py
lementpro/data/checkconnectionmodel.py
lementpro/data/checkconnectionresultmodel.py
lementpro/data/commentaddbyusermodel.py
lementpro/data/commentaddresultmodel.py
lementpro/data/commentemailextensionmodel.py
lementpro/data/commentextensionmodel.py
lementpro/data/commentpatchmodel.py
lementpro/data/companycontactdetailsmodel.py
lementpro/data/companycontactdetailspatchmodel.py
lementpro/data/companyextensionmodel.py
lementpro/data/companyinfodetailedmodel.py
lementpro/data/companyinfoextendedmodel.py
lementpro/data/companyinfomodel.py
lementpro/data/companylicensemodel.py
lementpro/data/companymailboxaddmodel.py
lementpro/data/companymailboxaddresultmodel.py
lementpro/data/companymailboxextendedmodel.py
lementpro/data/companymailboxpatchmodel.py
lementpro/data/companypasswordpolicymodel.py
lementpro/data/companypasswordpolicypatchmodel.py
lementpro/data/companypatchmodel.py
lementpro/data/departmentaddmodel.py
lementpro/data/departmentaddresultmodel.py
lementpro/data/departmentbosssetmodel.py
lementpro/data/departmentbossuserinfomodel.py
lementpro/data/departmentinfoextendedmodel.py
lementpro/data/departmentinfomodel.py
lementpro/data/departmentpagingmodel.py
lementpro/data/departmenttreemodel.py
lementpro/data/departmentupdatemodel.py
lementpro/data/emailaddressmodel.py
lementpro/data/errorresponse.py
lementpro/data/etaginfomodel.py
lementpro/data/fileinfomodel.py
lementpro-1.0.0.dist-info/METADATA
lementpro-1.0.0.dist-info/WHEEL
lementpro-1.0.0.dist-info/top_level.txt
lementpro-1.0.0.dist-info/RECORD
