Metadata-Version: 2.1
Name: lementpro
Version: 1.0.0
Summary: simple SDK for working with sodis api
Home-page: https://github.com/your_username/your_package_name
Author: Mikhail Chupilnick
Author-email: mchupilnik@sodislab.com
License: UNKNOWN
Platform: UNKNOWN
Classifier: Programming Language :: Python :: 3
Classifier: License :: OSI Approved :: MIT License
Classifier: Operating System :: OS Independent
Requires-Python: >=3.6
Requires-Dist: requests (>=2.0.0)
